software1checker/__init__.py
software1checker/__main__.py
software1checker/main.py
software1checker-0.0.7.dist-info/LICENSE.md
software1checker-0.0.7.dist-info/METADATA
software1checker-0.0.7.dist-info/WHEEL
software1checker-0.0.7.dist-info/entry_points.txt
software1checker-0.0.7.dist-info/top_level.txt
software1checker-0.0.7.dist-info/RECORD
