Metadata-Version: 2.1
Name: software1checker
Version: 0.0.7
Summary: A test runner for the software 1 course
Author: Noam Zaks
Classifier: Programming Language :: Python :: 3
Classifier: License :: OSI Approved :: MIT License
Classifier: Operating System :: OS Independent
Requires-Python: >=3.6
License-File: LICENSE.md
